atomrss/__init__.py
atomrss/atom.py
atomrss/exceptions.py
atomrss/feed.py
atomrss/rss.py
atomrss-0.1.dist-info/DESCRIPTION.rst
atomrss-0.1.dist-info/METADATA
atomrss-0.1.dist-info/RECORD
atomrss-0.1.dist-info/WHEEL
atomrss-0.1.dist-info/metadata.json
atomrss-0.1.dist-info/top_level.txt
