Metadata-Version: 2.0
Name: atomrss
Version: 0.1
Summary: Atom and RSS parser
Home-page: https://github.com/DasIch/atomrss
Author: Daniel Neuhäuser
Author-email: ich@danielneuhaeuser.de
License: UNKNOWN
Platform: UNKNOWN
Requires-Dist: lxml
Requires-Dist: python-dateutil
Requires-Dist: structlog
